Metadata-Version: 2.1
Name: papka_kulikov_v_m
Version: 0.0.1
Summary: Kulikov Package
Author: Kulikov V.M.
Author-email: your@domain.com
